muiscaenergy_common/__init__.py
muiscaenergy_common/run.py
muiscaenergy_common/src/__init__.py
muiscaenergy_common/src/timeseries/__init__.py
muiscaenergy_common/src/timeseries/series_base.py
muiscaenergy_common/test/__init__.py
muiscaenergy_common/test/run_test.py
muiscaenergy_common/test/timeseries/__init__.py
muiscaenergy_common/test/timeseries/series_base.py
muiscaenergy_common-0.0.2.dist-info/LICENSE
muiscaenergy_common-0.0.2.dist-info/METADATA
muiscaenergy_common-0.0.2.dist-info/WHEEL
muiscaenergy_common-0.0.2.dist-info/top_level.txt
muiscaenergy_common-0.0.2.dist-info/RECORD
